tirf_trajectory-0.0.6.dist-info/METADATA
tirf_trajectory-0.0.6.dist-info/top_level.txt
tirf_trajectory-0.0.6.dist-info/RECORD
tirf_trajectory-0.0.6.dist-info/WHEEL
tirf_trajectory/bootstrap.cpython-310-x86_64-linux-gnu.so
tirf_trajectory/__init__.py
