Metadata-Version: 2.1
Name: tirf-trajectory
Version: 0.0.6
Summary: TIRF Trajectory
Author: Kan Liu
Author-email: liuk@wipm.ac.cn
Requires-Python: >=3.6
Requires-Dist: numpy
Requires-Dist: nonstationarity
Requires-Dist: scipy
Requires-Dist: plotly
Requires-Dist: pandas
Requires-Dist: openpyxl
Requires-Dist: lmfit
Requires-Dist: param
Requires-Dist: panel
